dobot_utils/__init__.py
dobot_utils/dobot_api.py
dobot_utils/types.py
dobot_utils/util.py
dobot_utils-1.0.1.dist-info/LICENSE
dobot_utils-1.0.1.dist-info/METADATA
dobot_utils-1.0.1.dist-info/WHEEL
dobot_utils-1.0.1.dist-info/top_level.txt
dobot_utils-1.0.1.dist-info/RECORD
