Metadata-Version: 2.1
Name: dobot-utils
Version: 1.0.1
Summary: An ergonomic and type-hinted Python API for Dobot Products TCP-IP Protocol
Author-email: Calastrophe <vmxoperation@proton.me>
Project-URL: Homepage, https://github.com/Calastrophe/dobot_utils
Project-URL: Bug Tracker, https://github.com/Calastrophe/dobot_utils/issues
Classifier: Programming Language :: Python :: 3.10
Classifier: License :: OSI Approved :: GNU General Public License v3 (GPLv3)
Classifier: Operating System :: OS Independent
Requires-Python: >=3.10
License-File: LICENSE
Requires-Dist: numpy
Requires-Dist: StrEnum
